__init__.py
time_helper.py
luca_helpers-0.0.4.dist-info/LICENSE
luca_helpers-0.0.4.dist-info/METADATA
luca_helpers-0.0.4.dist-info/WHEEL
luca_helpers-0.0.4.dist-info/top_level.txt
luca_helpers-0.0.4.dist-info/RECORD
