Metadata-Version: 2.1
Name: luca_helpers
Version: 0.0.4
Summary: A small package with helper functions
Author-email: alphonse luca <alphonseluca@163.com>
License: MIT License
Project-URL: Homepage, https://github.com/Zoneee/py_helpers
Project-URL: Issues, https://github.com/Zoneee/py_helpers/issues
Classifier: Programming Language :: Python :: 3
Classifier: License :: OSI Approved :: MIT License
Classifier: Operating System :: OS Independent
Requires-Python: >=3.6
License-File: LICENSE
